<?xml version="1.0" encoding="utf-8"?>
<Application>
  <Views Id="Views">
    <DetailView Id="Venta_DetailView">
      <Layout Id="Layout">
        <LayoutGroup Id="Main">
          <LayoutGroup Id="SimpleEditors">
            <TabbedGroup Id="Item1">
              <LayoutGroup Id="Item2">
                <LayoutItem Id="Nrc" ViewItem="Nrc" />
              </LayoutGroup>
            </TabbedGroup>
          </LayoutGroup>
        </LayoutGroup>
      </Layout>
    </DetailView>
  </Views>
</Application>